{
    "71583309": {
        "name": "Ноутбук Acer Aspire 3 A315-23-R7CZ (NX.HVTER.028)",
        "price": 36999,
        "Операционная система": "Windows 10 Домашняя x64",
        "Диагональ экрана": "15.6\"",
        "Разрешение экрана": "1366x768 Пикс",
        "Производитель процессора": "AMD",
        "Модель процессора": "Ryzen 3 3250U",
        "Тактовая частота": "2.6 ГГц",
        "Объем оперативной памяти": "8 ГБ",
        "Тип оперативной памяти": "DDR4",
        "Тип накопителя": "SSD",
        "Объем накопителя": "256 ГБ",
        "Производитель видеокарты": "AMD",
        "Модель видеокарты": "Radeon Graphics",
        "Цвет": "Черный"
    },
    "71640793": {
        "name": "Ноутбук HP 15s-eq2099ur (5D647EA)",
        "price": 64999,
        "Операционная система": "FreeDOS",
        "Диагональ экрана": "15.6\"",
        "Разрешение экрана": "1920x1080 Пикс",
        "Производитель процессора": "AMD",
        "Модель процессора": "Ryzen 5 5500U",
        "Тактовая частота": "2.1 ГГц",
        "Объем оперативной памяти": "16 ГБ",
        "Тип оперативной памяти": "DDR4",
        "Тип накопителя": "SSD",
        "Объем накопителя": "512 ГБ",
        "Производитель видеокарты": "AMD",
        "Модель видеокарты": "Radeon",
        "Цвет": "Серебристый"
    },
    "71575990": {
        "name": "Ноутбук Apple MacBook Pro 13 M1 8-core (8-core GPU)/16/256 Space Gray (Z11B)",
        "price": 170499,
        "Операционная система": "MacOS",
        "Диагональ экрана": "13.3\"",
        "Разрешение экрана": "2560x1600 Пикс",
        "Производитель процессора": "Apple",
        "Модель процессора": "Apple M1",
        "Объем оперативной памяти": "16 ГБ",
        "Тип накопителя": "SSD",
        "Объем накопителя": "256 ГБ",
        "Производитель видеокарты": "Apple",
        "Сенсорная панель Touch Bar": "Есть",
        "Цвет": "Серый"
    },
    "71622327": {
        "name": "Ноутбук Honor MagicBook 14 R5/8/512 Space Grey (NMH-WDQ9HN)",
        "price": 69999,
        "Операционная система": "Windows 10 Домашняя x64",
        "Диагональ экрана": "14\"",
        "Разрешение экрана": "1920x1080 Пикс",
        "Производитель процессора": "AMD",
        "Модель процессора": "Ryzen 5 5500U",
        "Тактовая частота": "2.1 ГГц",
        "Объем оперативной памяти": "8 ГБ",
        "Тип оперативной памяти": "DDR4",
        "Тип накопителя": "SSD",
        "Объем накопителя": "512 ГБ",
        "Производитель видеокарты": "AMD",
        "Модель видеокарты": "Radeon Graphics",
        "Цвет": "Серый"
    },
    "71604212": {
        "name": "Ультрабук Acer Swift 1 SF114-34-C564 (NX.A74ER.002)",
        "price": 39999,
        "Операционная система": "Windows 10 Домашняя",
        "Диагональ экрана": "14\"",
        "Разрешение экрана": "1920x1080 Пикс",
        "Производитель процессора": "Intel",
        "Модель процессора": "Celeron N4500",
        "Тактовая частота": "1.1 ГГц",
        "Объем оперативной памяти": "4 ГБ",
        "Тип оперативной памяти": "DDR4",
        "Тип накопителя": "SSD",
        "Объем накопителя": "128 ГБ",
        "Производитель видеокарты": "Intel",
        "Модель видеокарты": "HD Graphics 615",
        "Цвет": "Золотистый"
    },
    "71641374": {
        "name": "Ультрабук HUAWEI MateBook 16 16+512GB Space Grey (CREM-WFD9)",
        "price": 99999,
        "Операционная система": "Windows 10",
        "Диагональ экрана": "16\"",
        "Разрешение экрана": "2520x1680 Пикс",
        "Производитель процессора": "AMD",
        "Модель процессора": "Ryzen 7 5800H",
        "Тактовая частота": "3.2 ГГц",
        "Объем оперативной памяти": "16 ГБ",
        "Тип оперативной памяти": "DDR4",
        "Тип накопителя": "SSD",
        "Объем накопителя": "512 ГБ",
        "Производитель видеокарты": "AMD",
        "Модель видеокарты": "Radeon Graphics",
        "Цвет": "Серый"
    },
    "71615577": {
        "name": "Ноутбук Haier U1520EM",
        "price": 17999,
        "Операционная система": "Windows 10 Домашняя",
        "Диагональ экрана": "15.6\"",
        "Разрешение экрана": "1920x1080 Пикс",
        "Производитель процессора": "Intel",
        "Модель процессора": "Celeron N4020",
        "Тактовая частота": "1.1 ГГц",
        "Объем оперативной памяти": "4 ГБ",
        "Тип оперативной памяти": "LPDDR4",
        "Тип накопителя": "eMMC",
        "Объем накопителя": "64 ГБ",
        "Производитель видеокарты": "Intel",
        "Модель видеокарты": "Intel UHD Graphics 600",
        "Цвет": "Серебристый"
    },
    "71611846": {
        "name": "Ноутбук HP Pavilion 14-ec0010ur (491K0EA)",
        "price": 54999,
        "Операционная система": "Windows 10 Домашняя x64",
        "Диагональ экрана": "14\"",
        "Разрешение экрана": "1920x1080 Пикс",
        "Производитель процессора": "AMD",
        "Модель процессора": "Ryzen 3 5300U",
        "Тактовая частота": "2.6 ГГц",
        "Объем оперативной памяти": "8 ГБ",
        "Тип оперативной памяти": "DDR4",
        "Тип накопителя": "SSD",
        "Объем накопителя": "512 ГБ",
        "Производитель видеокарты": "AMD",
        "Модель видеокарты": "AMD Radeon Graphics",
        "Цвет": "Синий"
    },
    "71634167": {
        "name": "Ноутбук Acer Swift 3 SF314-43-R1KU (NX.ACPER.00A)",
        "price": 69999,
        "Операционная система": "Windows 11 Домашняя x64",
        "Диагональ экрана": "14\"",
        "Разрешение экрана": "1920x1080 Пикс",
        "Производитель процессора": "AMD",
        "Модель процессора": "Ryzen 5 5500U",
        "Тактовая частота": "2.1 ГГц",
        "Объем оперативной памяти": "8 ГБ",
        "Тип оперативной памяти": "DDR4",
        "Тип накопителя": "SSD",
        "Объем накопителя": "512 ГБ",
        "Производитель видеокарты": "AMD",
        "Модель видеокарты": "Radeon Vega 7",
        "Цвет": "Синий"
    },
    "71641947": {
        "name": "Ноутбук HP 17-cp0126ur (5D666EA)",
        "price": 53999,
        "Операционная система": "FreeDOS",
        "Диагональ экрана": "17.3\"",
        "Разрешение экрана": "1920x1080 Пикс",
        "Производитель процессора": "AMD",
        "Модель процессора": "Ryzen 5 5500U",
        "Тактовая частота": "2.1 ГГц",
        "Объем оперативной памяти": "16 ГБ",
        "Тип оперативной памяти": "DDR4",
        "Тип накопителя": "SSD",
        "Объем накопителя": "512 ГБ",
        "Производитель видеокарты": "AMD",
        "Модель видеокарты": "Radeon",
        "Цвет": "Серебристый"
    },
    "71630900": {
        "name": "Ноутбук ASUS R565EA-EJ1076T",
        "price": 46999,
        "Операционная система": "Windows 10 Домашняя x64",
        "Диагональ экрана": "15.6\"",
        "Разрешение экрана": "1920x1080 Пикс",
        "Производитель процессора": "Intel",
        "Модель процессора": "Core i3-1115G4",
        "Тактовая частота": "3 ГГц",
        "Объем оперативной памяти": "8 ГБ",
        "Тип оперативной памяти": "DDR4",
        "Тип накопителя": "SSD",
        "Объем накопителя": "256 ГБ",
        "Производитель видеокарты": "Intel",
        "Модель видеокарты": "Intel UHD Graphics",
        "Цвет": "Серый"
    },
    "71630904": {
        "name": "Ноутбук ASUS VivoBook Pro 15 OLED K3500PC-L1057T",
        "price": 86999,
        "Операционная система": "Windows 10 Домашняя x64",
        "Диагональ экрана": "15.6\"",
        "Разрешение экрана": "1920x1080 Пикс",
        "Производитель процессора": "Intel",
        "Модель процессора": "Core i5-11300H",
        "Тактовая частота": "3.1 ГГц",
        "Объем оперативной памяти": "8 ГБ",
        "Тип оперативной памяти": "DDR4",
        "Тип накопителя": "SSD",
        "Объем накопителя": "512 ГБ",
        "Объем памяти Intel Optane": "32 ГБ",
        "Производитель видеокарты": "NVIDIA",
        "Модель видеокарты": "GeForce RTX 3050",
        "Объем видеопамяти": "4 ГБ",
        "Цвет": "Синий"
    },
    "71634656": {
        "name": "Ноутбук HUAWEI MateBook D 15 8+512GB Space Grey (BoD-WDH9)",
        "price": 69999,
        "Операционная система": "Windows 11 Домашняя x64",
        "Диагональ экрана": "15.6\"",
        "Разрешение экрана": "1920x1080 Пикс",
        "Производитель процессора": "Intel",
        "Модель процессора": "Core i5-1135G7",
        "Тактовая частота": "2.4 ГГц",
        "Объем оперативной памяти": "8 ГБ",
        "Тип оперативной памяти": "DDR4",
        "Тип накопителя": "SSD",
        "Объем накопителя": "512 ГБ",
        "Производитель видеокарты": "Intel",
        "Модель видеокарты": "Iris Xe Graphics",
        "Цвет": "Серый"
    },
    "71581540": {
        "name": "Ноутбук-трансформер Lenovo IdeaPad Flex 3 11ADA05 (82G4001NRU)",
        "price": 26999,
        "Операционная система": "Windows 10 Домашняя в S-режиме",
        "Диагональ экрана": "11.6\"",
        "Разрешение экрана": "1366x768 Пикс",
        "Сенсорный": "Есть",
        "Производитель процессора": "AMD",
        "Тактовая частота": "1.2 ГГц",
        "Объем оперативной памяти": "4 ГБ",
        "Тип оперативной памяти": "DDR4",
        "Тип накопителя": "eMMC",
        "Объем накопителя": "64 ГБ",
        "Производитель видеокарты": "AMD",
        "Модель видеокарты": "Radeon Graphics",
        "Цвет": "Серый"
    },
    "71641945": {
        "name": "Ноутбук HP 17-cn0101ur (5D5G4EA)",
        "price": 59999,
        "Операционная система": "Windows 11 Домашняя x64",
        "Диагональ экрана": "17.3\"",
        "Разрешение экрана": "1920x1080 Пикс",
        "Производитель процессора": "Intel",
        "Модель процессора": "Core i5-1135G7",
        "Тактовая частота": "2.4 ГГц",
        "Объем оперативной памяти": "8 ГБ",
        "Тип оперативной памяти": "DDR4",
        "Тип накопителя": "SSD",
        "Объем накопителя": "512 ГБ",
        "Производитель видеокарты": "Intel",
        "Модель видеокарты": "Iris Xe Graphics",
        "Цвет": "Серебристый"
    },
    "71625565": {
        "name": "Ноутбук Irbis NB264",
        "price": 15999,
        "Операционная система": "Windows 10 Профессиональная",
        "Диагональ экрана": "14.1\"",
        "Разрешение экрана": "1920x1080 Пикс",
        "Производитель процессора": "Intel",
        "Модель процессора": "Celeron N4020",
        "Тактовая частота": "1.1 ГГц",
        "Объем оперативной памяти": "4 ГБ",
        "Тип оперативной памяти": "LPDDR4",
        "Тип накопителя": "eMMC",
        "Объем накопителя": "128 ГБ",
        "Производитель видеокарты": "Intel",
        "Модель видеокарты": "Intel UHD Graphics 600",
        "Цвет": "Черный"
    },
    "71602458": {
        "name": "Ноутбук HP 15s-eq1364ur (491L5EA)",
        "price": 42999,
        "Операционная система": "Windows 10 Домашняя x64",
        "Диагональ экрана": "15.6\"",
        "Разрешение экрана": "1920x1080 Пикс",
        "Производитель процессора": "AMD",
        "Модель процессора": "Ryzen 3 4300U",
        "Тактовая частота": "2.7 ГГц",
        "Объем оперативной памяти": "8 ГБ",
        "Тип оперативной памяти": "DDR4",
        "Тип накопителя": "SSD",
        "Объем накопителя": "256 ГБ",
        "Производитель видеокарты": "AMD",
        "Модель видеокарты": "Radeon Graphics",
        "Цвет": "Белый"
    },
    "71612421": {
        "name": "Ноутбук HUAWEI MateBook X Pro 16+512GB Space Grey (MACHD-WFE9Q)",
        "price": 134999,
        "Операционная система": "Windows 10 Домашняя x64",
        "Диагональ экрана": "13.9\"",
        "Разрешение экрана": "3000x2000 Пикс",
        "Производитель процессора": "Intel",
        "Модель процессора": "Core i7-1165G7",
        "Тактовая частота": "2.8 ГГц",
        "Объем оперативной памяти": "16 ГБ",
        "Тип оперативной памяти": "LPDDR4X",
        "Тип накопителя": "SSD",
        "Объем накопителя": "512 ГБ",
        "Производитель видеокарты": "Intel",
        "Модель видеокарты": "Iris Xe Graphics",
        "Цвет": "Серый"
    },
    "71615573": {
        "name": "Ноутбук Haier U1520SM",
        "price": 25999,
        "Операционная система": "Windows 10 Домашняя",
        "Диагональ экрана": "15.6\"",
        "Разрешение экрана": "1920x1080 Пикс",
        "Производитель процессора": "Intel",
        "Модель процессора": "Celeron N4020",
        "Тактовая частота": "1.1 ГГц",
        "Объем оперативной памяти": "4 ГБ",
        "Тип оперативной памяти": "LPDDR4",
        "Тип накопителя": "SSD",
        "Объем накопителя": "128 ГБ",
        "Производитель видеокарты": "Intel",
        "Модель видеокарты": "Intel UHD Graphics 600",
        "Цвет": "Серебристый"
    },
    "71644907": {
        "name": "Игровой ноутбук Lenovo Legion 5 15ACH6A (82NW0046RU)",
        "price": 119999,
        "Игровой ноутбук": "Есть",
        "Операционная система": "Windows 11 Домашняя x64",
        "Диагональ экрана": "15.6\"",
        "Разрешение экрана": "1920x1080 Пикс",
        "Производитель процессора": "AMD",
        "Модель процессора": "Ryzen 5 5600H",
        "Тактовая частота": "3.3 ГГц",
        "Объем оперативной памяти": "16 ГБ",
        "Тип оперативной памяти": "DDR4",
        "Тип накопителя": "SSD",
        "Объем накопителя": "512 ГБ",
        "Производитель видеокарты": "AMD",
        "Модель видеокарты": "RX 6600M",
        "Объем видеопамяти": "8 ГБ",
        "Цвет": "Черный"
    },
    "71632897": {
        "name": "Ноутбук Honor MagicBook View 14 i5/16/512 Blue (HGE-W56)",
        "price": 99999,
        "Операционная система": "Windows 11 Домашняя x64",
        "Диагональ экрана": "14.2\"",
        "Разрешение экрана": "2520x1680 Пикс",
        "Сенсорный": "Есть",
        "Производитель процессора": "Intel",
        "Модель процессора": "Core i5-11320H",
        "Тактовая частота": "2.5 ГГц",
        "Объем оперативной памяти": "16 ГБ",
        "Тип оперативной памяти": "LPDDR4X",
        "Тип накопителя": "SSD",
        "Объем накопителя": "512 ГБ",
        "Производитель видеокарты": "Intel",
        "Модель видеокарты": "Intel Iris Xe Graphics",
        "Цвет": "Синий"
    },
    "71623428": {
        "name": "Ноутбук ASUS VivoBook 15 R528EP-BQ438T",
        "price": 56999,
        "Операционная система": "Windows 10 Домашняя",
        "Диагональ экрана": "15.6\"",
        "Разрешение экрана": "1920x1080 Пикс",
        "Производитель процессора": "Intel",
        "Модель процессора": "Core i3-1115G4",
        "Тактовая частота": "3 ГГц",
        "Объем оперативной памяти": "8 ГБ",
        "Тип оперативной памяти": "DDR4",
        "Тип накопителя": "SSD",
        "Объем накопителя": "256 ГБ",
        "Производитель видеокарты": "NVIDIA",
        "Модель видеокарты": "GeForce MX330",
        "Объем видеопамяти": "2 ГБ",
        "Сенсорная панель Touch Bar": "Есть",
        "Цвет": "Черный"
    },
    "71646475": {
        "name": "Игровой ноутбук Acer Aspire 7 A715-42G-R3FW (NH.QDLER.003)",
        "price": 99999,
        "Игровой ноутбук": "Есть",
        "Операционная система": "Windows 11 Домашняя x64",
        "Диагональ экрана": "15.6\"",
        "Разрешение экрана": "1920x1080 Пикс",
        "Производитель процессора": "AMD",
        "Модель процессора": "Ryzen 5 5500U",
        "Тактовая частота": "2.1 ГГц",
        "Объем оперативной памяти": "16 ГБ",
        "Тип оперативной памяти": "DDR4",
        "Тип накопителя": "SSD",
        "Объем накопителя": "512 ГБ",
        "Производитель видеокарты": "NVIDIA",
        "Модель видеокарты": "GeForce RTX 3050 Ti",
        "Объем видеопамяти": "4 ГБ",
        "Цвет": "Черный"
    },
    "71614045": {
        "name": "Ноутбук Irbis NB266",
        "price": 22999,
        "Операционная система": "Windows 10",
        "Диагональ экрана": "15.6\"",
        "Разрешение экрана": "1920x1080 Пикс",
        "Производитель процессора": "Intel",
        "Модель процессора": "Pentium J3710",
        "Тактовая частота": "1.6 ГГц",
        "Объем оперативной памяти": "4 ГБ",
        "Тип накопителя": "eMMC",
        "Объем накопителя": "128 ГБ",
        "Производитель видеокарты": "Intel",
        "Модель видеокарты": "HD Graphics",
        "Цвет": "Серый"
    },
    "71639261": {
        "name": "Ноутбук ASUS VivoBook S14 S433JQ-EB076T",
        "price": 59999,
        "Операционная система": "Windows 10 Домашняя x64",
        "Диагональ экрана": "14\"",
        "Разрешение экрана": "1920x1080 Пикс",
        "Производитель процессора": "Intel",
        "Модель процессора": "Core i5-1035G1",
        "Тактовая частота": "1 ГГц",
        "Объем оперативной памяти": "8 ГБ",
        "Тип оперативной памяти": "DDR4",
        "Тип накопителя": "SSD",
        "Объем накопителя": "512 ГБ",
        "Производитель видеокарты": "NVIDIA",
        "Модель видеокарты": "GeForce MX350",
        "Объем видеопамяти": "2 ГБ",
        "Цвет": "Черный"
    },
    "71640700": {
        "name": "Ноутбук HUAWEI MateBook D 15 BoD-WFE9 16+512GB Space Grey",
        "price": 89999,
        "Операционная система": "Windows 11 Домашняя x64",
        "Диагональ экрана": "15.6\"",
        "Разрешение экрана": "1920x1080 Пикс",
        "Производитель процессора": "Intel",
        "Модель процессора": "Core i7-1165G7",
        "Тактовая частота": "2.8 ГГц",
        "Объем оперативной памяти": "16 ГБ",
        "Тип оперативной памяти": "DDR4",
        "Тип накопителя": "SSD",
        "Объем накопителя": "512 ГБ",
        "Производитель видеокарты": "Intel",
        "Модель видеокарты": "Intel Iris Xe Graphics",
        "Цвет": "Серый"
    },
    "71645073": {
        "name": "Игровой ноутбук Acer Nitro AN517-54-77PS (NH.QFCER.006)",
        "price": 159999,
        "Игровой ноутбук": "Есть",
        "Операционная система": "Windows 11 Домашняя x64",
        "Диагональ экрана": "17.3\"",
        "Разрешение экрана": "1920x1080 Пикс",
        "Производитель процессора": "Intel",
        "Модель процессора": "Core i7-11800H",
        "Тактовая частота": "2.3 ГГц",
        "Объем оперативной памяти": "16 ГБ",
        "Тип оперативной памяти": "DDR3L",
        "Тип накопителя": "SSD",
        "Объем накопителя": "512 ГБ",
        "Производитель видеокарты": "NVIDIA",
        "Модель видеокарты": "GeForce RTX 3070 для ноутбуков",
        "Объем видеопамяти": "8 ГБ",
        "Цвет": "Черный"
    },
    "71615550": {
        "name": "Ноутбук-трансформер Irbis NB121",
        "price": 16999,
        "Операционная система": "Windows 10",
        "Диагональ экрана": "11.6\"",
        "Разрешение экрана": "1366x768 Пикс",
        "Сенсорный": "Есть",
        "Производитель процессора": "Intel",
        "Модель процессора": "Celeron N4020",
        "Тактовая частота": "1.1 ГГц",
        "Объем оперативной памяти": "4 ГБ",
        "Тип оперативной памяти": "LPDDR3",
        "Тип накопителя": "eMMC",
        "Объем накопителя": "64 ГБ",
        "Производитель видеокарты": "Intel",
        "Модель видеокарты": "Intel UHD Graphics 600",
        "Цвет": "Черный"
    },
    "71630004": {
        "name": "Ноутбук Lenovo IdeaPad 3 15IIL05 (81WE01BFRU)",
        "price": 44999,
        "Диагональ экрана": "15.6\"",
        "Разрешение экрана": "1920x1080 Пикс",
        "Производитель процессора": "Intel",
        "Модель процессора": "Core i3-1005G1",
        "Тактовая частота": "1.2 ГГц",
        "Объем оперативной памяти": "8 ГБ",
        "Тип оперативной памяти": "DDR4",
        "Тип накопителя": "SSD",
        "Объем накопителя": "256 ГБ",
        "Производитель видеокарты": "Intel",
        "Модель видеокарты": "Intel UHD Graphics",
        "Цвет": "Серебристый"
    },
    "71626049": {
        "name": "Ноутбук HUAWEI MateBook 14S HKD-W76 16+1TB Space Grey с платформой Intel Evo",
        "price": 129999,
        "Операционная система": "Windows 10 Домашняя x64",
        "Диагональ экрана": "14.2\"",
        "Разрешение экрана": "2520x1680 Пикс",
        "Сенсорный": "Есть",
        "Производитель процессора": "Intel",
        "Модель процессора": "Core i7-11370H",
        "Объем оперативной памяти": "16 ГБ",
        "Тип оперативной памяти": "LPDDR4X",
        "Тип накопителя": "SSD",
        "Объем накопителя": "1 ТБ",
        "Производитель видеокарты": "Intel",
        "Модель видеокарты": "Iris Graphics",
        "Цвет": "Серый"
    },
    "71642806": {
        "name": "Ноутбук Honor MagicBook X15 i5/16/512 Space Gray (BBR-WAH9)",
        "price": 69999,
        "Операционная система": "Windows 10 Домашняя x64",
        "Диагональ экрана": "15.6\"",
        "Разрешение экрана": "1920x1080 Пикс",
        "Производитель процессора": "Intel",
        "Модель процессора": "Core i5-10210U",
        "Тактовая частота": "1.6 ГГц",
        "Объем оперативной памяти": "16 ГБ",
        "Тип оперативной памяти": "DDR4",
        "Тип накопителя": "SSD",
        "Объем накопителя": "512 ГБ",
        "Производитель видеокарты": "Intel",
        "Модель видеокарты": "UHD Graphics",
        "Цвет": "Серый"
    },
    "71631268": {
        "name": "Ноутбук ASUS M513IA-BQ547T",
        "price": 64999,
        "Операционная система": "Windows 10 Домашняя",
        "Диагональ экрана": "15.6\"",
        "Разрешение экрана": "1920x1080 Пикс",
        "Производитель процессора": "AMD",
        "Модель процессора": "Ryzen 7 4700U",
        "Тактовая частота": "2 ГГц",
        "Объем оперативной памяти": "8 ГБ",
        "Тип оперативной памяти": "DDR4",
        "Тип накопителя": "SSD",
        "Объем накопителя": "512 ГБ",
        "Производитель видеокарты": "AMD",
        "Модель видеокарты": "Radeon Graphics",
        "Цвет": "Черный"
    },
    "71628638": {
        "name": "Ноутбук Honor MagicBook 15 R5/8/512 Silver (BMH-WDQ9HN)",
        "price": 69999,
        "Операционная система": "Windows 10 Домашняя x64",
        "Диагональ экрана": "15.6\"",
        "Разрешение экрана": "1920x1080 Пикс",
        "Производитель процессора": "AMD",
        "Модель процессора": "Ryzen 5 5500U",
        "Тактовая частота": "2.1 ГГц",
        "Объем оперативной памяти": "8 ГБ",
        "Тип оперативной памяти": "DDR4",
        "Тип накопителя": "SSD",
        "Объем накопителя": "512 ГБ",
        "Производитель видеокарты": "AMD",
        "Модель видеокарты": "Radeon Graphics",
        "Цвет": "Серебристый"
    },
    "71634150": {
        "name": "Ноутбук ASUS R214MA-GJ373T",
        "price": 21999,
        "Операционная система": "Windows 10 Домашняя",
        "Диагональ экрана": "11.6\"",
        "Разрешение экрана": "1366x768 Пикс",
        "Производитель процессора": "Intel",
        "Модель процессора": "Celeron N4020",
        "Тактовая частота": "1.1 ГГц",
        "Объем оперативной памяти": "4 ГБ",
        "Тип оперативной памяти": "DDR4",
        "Тип накопителя": "eMMC",
        "Объем накопителя": "128 ГБ",
        "Производитель видеокарты": "Intel",
        "Модель видеокарты": "Intel UHD Graphics 600",
        "Цвет": "Синий"
    },
    "71641259": {
        "name": "Ноутбук ASUS R429MA-BV1505W",
        "price": 25999,
        "Операционная система": "Windows 11 Домашняя",
        "Диагональ экрана": "14\"",
        "Разрешение экрана": "1366x768 Пикс",
        "Производитель процессора": "Intel",
        "Модель процессора": "Celeron N4020",
        "Тактовая частота": "1.1 ГГц",
        "Объем оперативной памяти": "4 ГБ",
        "Тип оперативной памяти": "DDR4",
        "Тип накопителя": "SSD",
        "Объем накопителя": "128 ГБ",
        "Производитель видеокарты": "Intel",
        "Модель видеокарты": "UHD Graphics 600",
        "Цвет": "Синий, Черный"
    },
    "71626200": {
        "name": "Ноутбук Acer Aspire 3 A315-57G (NX.HZRER.01V)",
        "price": 49999,
        "Операционная система": "Windows 10 Домашняя x64",
        "Диагональ экрана": "15.6\"",
        "Разрешение экрана": "1366x768 Пикс",
        "Производитель процессора": "Intel",
        "Модель процессора": "Core i3-1005G1",
        "Тактовая частота": "1.2 ГГц",
        "Объем оперативной памяти": "8 ГБ",
        "Тип оперативной памяти": "DDR4",
        "Тип накопителя": "SSD",
        "Объем накопителя": "256 ГБ",
        "Производитель видеокарты": "NVIDIA",
        "Модель видеокарты": "GeForce MX330",
        "Объем видеопамяти": "2 ГБ",
        "Цвет": "Черный"
    }
}